pyspark_supp/__init__.py
pyspark_supp-0.1.0.dist-info/LICENSE
pyspark_supp-0.1.0.dist-info/LICENSE.txt
pyspark_supp-0.1.0.dist-info/METADATA
pyspark_supp-0.1.0.dist-info/WHEEL
pyspark_supp-0.1.0.dist-info/top_level.txt
pyspark_supp-0.1.0.dist-info/RECORD
