Metadata-Version: 2.1
Name: pyspark-supp
Version: 0.1.0
Summary: Data Engineer Support PySpark Library
Home-page: https://github.com/joaocaemerer/pyspark-supp
Author: Fernando Caemerer
Author-email: fernando.caemerer@gmail.com
License: MIT
Keywords: dataengineer,pyspark,dataframe
License-File: LICENSE
License-File: LICENSE.txt
Requires-Dist: pyspark
